LICENCE.txt
README.md
setup.py
src/rpc_rfsoc_handler/__init__.py
src/rpc_rfsoc_handler/devicecontrol_pb2.py
src/rpc_rfsoc_handler/devicecontrol_pb2_grpc.py
src/rpc_rfsoc_handler/interaction_handler.py
src/rpc_rfsoc_handler.egg-info/PKG-INFO
src/rpc_rfsoc_handler.egg-info/SOURCES.txt
src/rpc_rfsoc_handler.egg-info/dependency_links.txt
src/rpc_rfsoc_handler.egg-info/requires.txt
src/rpc_rfsoc_handler.egg-info/top_level.txt