Metadata-Version: 2.1
Name: rpc_rfsoc_handler
Version: 1.1.0
Summary: a pip-installable handler
Home-page: 
Author: Pascal Stoever
Author-email: 
License: MIT
Keywords: example
License-File: LICENCE.txt
Requires-Dist: grpcio-tools
